navam_invest/__init__.py
navam_invest/cli.py
navam_invest/agents/__init__.py
navam_invest/agents/earnings_whisperer.py
navam_invest/agents/hedge_smith.py
navam_invest/agents/macro_lens.py
navam_invest/agents/macro_lens.py.bak
navam_invest/agents/news_sentry.py
navam_invest/agents/portfolio.py
navam_invest/agents/portfolio.py.bak
navam_invest/agents/quill.py
navam_invest/agents/quill.py.bak
navam_invest/agents/research.py
navam_invest/agents/research.py.bak
navam_invest/agents/risk_shield.py
navam_invest/agents/router.py
navam_invest/agents/screen_forge.py
navam_invest/agents/screen_forge.py.bak
navam_invest/agents/tax_scout.py
navam_invest/cache/__init__.py
navam_invest/cache/common_queries.py
navam_invest/cache/manager.py
navam_invest/config/__init__.py
navam_invest/config/settings.py
navam_invest/tools/__init__.py
navam_invest/tools/alpha_vantage.py
navam_invest/tools/file_reader.py
navam_invest/tools/finnhub.py
navam_invest/tools/fmp.py
navam_invest/tools/fred.py
navam_invest/tools/newsapi.py
navam_invest/tools/sec_edgar.py
navam_invest/tools/tiingo.py
navam_invest/tools/treasury.py
navam_invest/tools/yahoo_finance.py
navam_invest/tui/__init__.py
navam_invest/tui/app.py
navam_invest/utils/__init__.py
navam_invest/utils/api_checker.py
navam_invest/utils/report_saver.py
navam_invest/workflows/__init__.py
navam_invest/workflows/idea_discovery.py
navam_invest/workflows/investment_analysis.py
navam_invest/workflows/portfolio_protection.py
navam_invest/workflows/tax_optimization.py
navam_invest-0.1.42.dist-info/METADATA
navam_invest-0.1.42.dist-info/WHEEL
navam_invest-0.1.42.dist-info/entry_points.txt
navam_invest-0.1.42.dist-info/licenses/LICENSE
navam_invest-0.1.42.dist-info/RECORD
