Metadata-Version: 2.4
Name: navam-invest
Version: 0.1.42
Summary: AI agents and tools for the retail investor
Project-URL: Homepage, https://github.com/navam-io/navam-invest
Project-URL: Repository, https://github.com/navam-io/navam-invest
Project-URL: Issues, https://github.com/navam-io/navam-invest/issues
Author-email: navam-io <contact@navam.io>
License: MIT
License-File: LICENSE
Keywords: ai-agents,finance,investment,retail-investor,trading
Classifier: Development Status :: 3 - Alpha
Classifier: Intended Audience :: Financial and Insurance Industry
Classifier: License :: OSI Approved :: MIT License
Classifier: Programming Language :: Python :: 3
Classifier: Programming Language :: Python :: 3.9
Classifier: Programming Language :: Python :: 3.10
Classifier: Programming Language :: Python :: 3.11
Classifier: Programming Language :: Python :: 3.12
Classifier: Topic :: Office/Business :: Financial :: Investment
Requires-Python: >=3.9
Requires-Dist: anthropic>=0.40.0
Requires-Dist: duckdb>=1.0.0
Requires-Dist: httpx>=0.28.0
Requires-Dist: langchain-anthropic>=0.3.0
Requires-Dist: langchain-core>=0.3.0
Requires-Dist: langgraph>=0.2.0
Requires-Dist: pydantic-settings>=2.0.0
Requires-Dist: pydantic>=2.0.0
Requires-Dist: python-dotenv>=1.0.0
Requires-Dist: rich>=13.0.0
Requires-Dist: textual>=1.0.0
Requires-Dist: typer>=0.15.0
Requires-Dist: yfinance>=0.2.49
Provides-Extra: dev
Requires-Dist: black>=24.0.0; extra == 'dev'
Requires-Dist: mypy>=1.8.0; extra == 'dev'
Requires-Dist: pytest-asyncio>=0.24.0; extra == 'dev'
Requires-Dist: pytest-cov>=4.1.0; extra == 'dev'
Requires-Dist: pytest>=8.0.0; extra == 'dev'
Requires-Dist: ruff>=0.1.0; extra == 'dev'
Requires-Dist: textual-dev>=1.0.0; extra == 'dev'
